src/program_counter/program_counter.vhd
library ieee;
use ieee.std_logic_1164.all;
use ieee.numeric_std.all;

entity program_counter is
    port (
        clk    : in  std_logic;                    -- System clock
        rst    : in  std_logic;                    -- Global reset (active high)
        inc    : in  std_logic;                    -- Increment enable from control matrix
        pc_out : out std_logic_vector(3 downto 0)  -- 4-bit memory address output
    );
end entity program_counter;

architecture behavioral of program_counter is
    signal count : unsigned(3 downto 0) := (others => '0');
begin

    process(clk, rst)
    begin
        if rst = '1' then
            count <= (others => '0');
        elsif rising_edge(clk) then
            if inc = '1' then
                count <= count + 1;
            end if;
        end if;
    end process;

    pc_out <= std_logic_vector(count);

end architecture behavioral;

tb/unit/program_counter/tb_program_counter.vhd
library ieee;
use ieee.std_logic_1164.all;
use ieee.numeric_std.all;

entity tb_program_counter is
end entity tb_program_counter;

architecture sim of tb_program_counter is

    constant CLK_PERIOD : time := 20 ns;

    signal clk    : std_logic := '0';
    signal rst    : std_logic := '0';
    signal inc    : std_logic := '0';
    signal pc_out : std_logic_vector(3 downto 0);

    signal sim_end : boolean := false;

begin

    -- Instantiate Unit Under Test (UUT)
    uut: entity work.program_counter
        port map (
            clk    => clk,
            rst    => rst,
            inc    => inc,
            pc_out => pc_out
        );

    -- Clock Generation
    clk_gen: process
    begin
        while not sim_end loop
            clk <= '0';
            wait for CLK_PERIOD / 2;
            clk <= '1';
            wait for CLK_PERIOD / 2;
        end loop;
        wait;
    end process;

    -- Stimulus Process
    stim_proc: process
    begin
        report "--- Starting Program Counter Unit Test ---";

        -- Test Case 1: Reset Behavior
        rst <= '1';
        inc <= '0';
        wait for 40 ns;
        assert pc_out = "0000" 
            report "FAIL: PC should be 0000 on reset" severity failure;
        
        rst <= '0';
        wait for 20 ns;

        -- Test Case 2: Hold State when inc = '0'
        wait until falling_edge(clk);
        inc <= '0';
        wait for 3 * CLK_PERIOD;
        assert pc_out = "0000" 
            report "FAIL: PC changed value while inc = '0'" severity failure;
        report "SUCCESS: PC held value when disabled.";

        -- Test Case 3: Incrementing Counter
        report "--- Incrementing PC across cycles ---";
        wait until falling_edge(clk);
        inc <= '1';
        
        -- Step through 5 increments
        for i in 1 to 5 loop
            wait until rising_edge(clk);
        end loop;
        
        wait for 1 ns; -- Small delay for propagation
        assert pc_out = "0101" 
            report "FAIL: Expected PC = 0101 (5), got " & to_hstring(pc_out) severity failure;
        report "SUCCESS: PC incremented to 0101.";

        -- Test Case 4: Overflow / Wrap-Around Test (15 -> 0)
        report "--- Testing Counter Wrap-Around ---";
        -- Advance 10 more times (5 + 10 = 15 = "1111")
        for i in 1 to 10 loop
            wait until rising_edge(clk);
        end loop;
        
        wait for 1 ns;
        assert pc_out = "1111" 
            report "FAIL: Expected PC = 1111 (15), got " & to_hstring(pc_out) severity failure;

        -- One more increment should wrap around to 0
        wait until rising_edge(clk);
        wait for 1 ns;
        assert pc_out = "0000" 
            report "FAIL: PC did not wrap around to 0000" severity failure;
        report "SUCCESS: PC correctly wrapped around to 0000.";

        -- Disable incrementing
        inc <= '0';
        wait for 20 ns;

        sim_end <= true;
        report "=== PROGRAM COUNTER MODULE TEST PASSED ===";
        wait;
    end process;

end architecture sim;

wave/unit/program_counter/waveform.vcd
$date
  Sat Sep 19 15:40:50 2026
$end
$version
  GHDL v0
$end
$timescale
  1 fs
$end
$scope module standard $end
$upscope $end
$scope module textio $end
$upscope $end
$scope module std_logic_1164 $end
$upscope $end
$scope module numeric_std $end
$upscope $end
$scope module tb_program_counter $end
$var reg 1 ! clk $end
$var reg 1 " rst $end
$var reg 1 # inc $end
$var reg 4 $ pc_out[3:0] $end
$var reg 1 % sim_end $end
$scope module uut $end
$var reg 1 & clk $end
$var reg 1 ' rst $end
$var reg 1 ( inc $end
$var reg 4 ) pc_out[3:0] $end
$var reg 4 * count[3:0] $end
$upscope $end
$upscope $end
$enddefinitions $end
#0
0!
1"
0#
b0000 $
0%
0&
1'
0(
b0000 )
b0000 *
#10000000
1!
1&
#20000000
0!
0&
#30000000
1!
1&
#40000000
0!
0"
0&
0'
#50000000
1!
1&
#60000000
0!
0&
#70000000
1!
1&
#80000000
0!
0&
#90000000
1!
1&
#100000000
0!
0&
#110000000
1!
1&
#120000000
0!
1#
0&
1(
#130000000
1!
b0001 $
1&
b0001 )
b0001 *
#140000000
0!
0&
#150000000
1!
b0010 $
1&
b0010 )
b0010 *
#160000000
0!
0&
#170000000
1!
b0011 $
1&
b0011 )
b0011 *
#180000000
0!
0&
#190000000
1!
b0100 $
1&
b0100 )
b0100 *
#200000000
0!
0&
#210000000
1!
b0101 $
1&
b0101 )
b0101 *
#211000000
#220000000
0!
0&
#230000000
1!
b0110 $
1&
b0110 )
b0110 *
#240000000
0!
0&
#250000000
1!
b0111 $
1&
b0111 )
b0111 *
#260000000
0!
0&
#270000000
1!
b1000 $
1&
b1000 )
b1000 *
#280000000
0!
0&
#290000000
1!
b1001 $
1&
b1001 )
b1001 *
#300000000
0!
0&
#310000000
1!
b1010 $
1&
b1010 )
b1010 *
#320000000
0!
0&
#330000000
1!
b1011 $
1&
b1011 )
b1011 *
#340000000
0!
0&
#350000000
1!
b1100 $
1&
b1100 )
b1100 *
#360000000
0!
0&
#370000000
1!
b1101 $
1&
b1101 )
b1101 *
#380000000
0!
0&
#390000000
1!
b1110 $
1&
b1110 )
b1110 *
#400000000
0!
0&
#410000000
1!
b1111 $
1&
b1111 )
b1111 *
#411000000
#420000000
0!
0&
#430000000
1!
b0000 $
1&
b0000 )
b0000 *
#431000000
0#
0(
#440000000
0!
0&
#450000000
1!
1&
#451000000
1%
