src/ring_counter/ring_counter.vhd
library ieee;
use ieee.std_logic_1164.all;

entity ring_counter is
    port (
        clk   : in  std_logic;                    -- System clock
        rst   : in  std_logic;                    -- Global reset (active high)
        t_out : out std_logic_vector(6 downto 0)  -- 7-bit one-hot T-state vector (T1 to T7)
    );
end entity ring_counter;

architecture behavioral of ring_counter is
    signal t_reg : std_logic_vector(6 downto 0) := "0000001";
begin

    process(clk, rst)
    begin
        if rst = '1' then
            t_reg <= "0000001"; -- Reset to T1 state
        elsif rising_edge(clk) then
            -- Rotate left: bit 6 wraps around to bit 0
            t_reg <= t_reg(5 downto 0) & t_reg(6);
        end if;
    end process;

    t_out <= t_reg;

end architecture behavioral;

tb/unit/ring_counter/tb_ring_counter.vhd
library ieee;
use ieee.std_logic_1164.all;

entity tb_ring_counter is
end entity tb_ring_counter;

architecture sim of tb_ring_counter is

    constant CLK_PERIOD : time := 20 ns;

    signal clk   : std_logic := '0';
    signal rst   : std_logic := '0';
    signal t_out : std_logic_vector(6 downto 0);

    signal sim_end : boolean := false;

    -- Expected T-states in sequence
    type t_state_array is array (0 to 6) of std_logic_vector(6 downto 0);
    constant EXPECTED_STATES : t_state_array := (
        "0000001", -- T1
        "0000010", -- T2
        "0000100", -- T3
        "0001000", -- (Wait - strictly 7-bit one-hot)
        "0010000", -- T4
        "0100000", -- T5
        "1000000"  -- T6 (Note: T1..T7 index mapped below)
    );

begin

    -- Instantiate Unit Under Test (UUT)
    uut: entity work.ring_counter
        port map (
            clk   => clk,
            rst   => rst,
            t_out => t_out
        );

    -- Clock Generation
    clk_gen: process
    begin
        while not sim_end loop
            clk <= '0';
            wait for CLK_PERIOD / 2;
            clk <= '1';
            wait for CLK_PERIOD / 2;
        end loop;
        wait;
    end process;

    -- Stimulus Process
    stim_proc: process
        -- Expected sequence for T1 through T7
        type seq_array is array (1 to 7) of std_logic_vector(6 downto 0);
        constant SEQ : seq_array := (
            1 => "0000001", -- T1
            2 => "0000010", -- T2
            3 => "0000100", -- T3
            4 => "0001000", -- T4
            5 => "0010000", -- T5
            6 => "0100000", -- T6
            7 => "1000000"  -- T7
        );
    begin
        report "--- Starting Ring Counter Unit Test ---";

        -- Test Case 1: Initial Reset Behavior
        rst <= '1';
        wait for 40 ns;
        assert t_out = "0000001"
            report "FAIL: Ring counter should be T1 (0000001) on reset" severity failure;
        
        rst <= '0';
        wait for 10 ns;

        -- Test Case 2: Verify Full T1 -> T7 Sequence
        report "--- Testing T1 to T7 Rotation Sequence ---";
        for step in 1 to 7 loop
            assert t_out = SEQ(step)
                report "FAIL: Step " & integer'image(step) & 
                       " expected " & to_string(SEQ(step)) & 
                       ", got " & to_string(t_out) severity failure;
            report "State T" & integer'image(step) & ": " & to_string(t_out);
            wait until rising_edge(clk);
            wait for 1 ns; -- Propagation settling time
        end loop;

        -- Test Case 3: Verify Wrap-Around Back to T1
        report "--- Testing Wrap-Around to T1 ---";
        assert t_out = "0000001"
            report "FAIL: Ring counter failed to wrap around to T1 (0000001)" severity failure;
        report "SUCCESS: Wrapped back to T1 correctly.";

        -- Test Case 4: Asynchronous / Synchronous Mid-Cycle Reset
        report "--- Testing Mid-Cycle Reset ---";
        -- Advance to T3
        wait until rising_edge(clk);
        wait until rising_edge(clk);
        wait for 1 ns;
        assert t_out = "0000100" report "FAIL: Should be at T3" severity failure;

        -- Apply reset
        rst <= '1';
        wait for 20 ns;
        assert t_out = "0000001" report "FAIL: Reset failed to restore T1" severity failure;
        
        rst <= '0';
        wait for 20 ns;

        sim_end <= true;
        report "=== RING COUNTER MODULE TEST PASSED ===";
        wait;
    end process;

end architecture sim;

wave/unit/ring-counter/waveform.vcd
$date
  Sat Sep 19 15:47:59 2026
$end
$version
  GHDL v0
$end
$timescale
  1 fs
$end
$scope module standard $end
$upscope $end
$scope module textio $end
$upscope $end
$scope module std_logic_1164 $end
$upscope $end
$scope module tb_ring_counter $end
$var reg 1 ! clk $end
$var reg 1 " rst $end
$var reg 7 # t_out[6:0] $end
$var reg 1 $ sim_end $end
$scope module uut $end
$var reg 1 % clk $end
$var reg 1 & rst $end
$var reg 7 ' t_out[6:0] $end
$var reg 7 ( t_reg[6:0] $end
$upscope $end
$upscope $end
$enddefinitions $end
#0
0!
1"
b0000001 #
0$
0%
1&
b0000001 '
b0000001 (
#10000000
1!
1%
#20000000
0!
0%
#30000000
1!
1%
#40000000
0!
0"
0%
0&
#50000000
1!
b0000010 #
1%
b0000010 '
b0000010 (
#51000000
#60000000
0!
0%
#70000000
1!
b0000100 #
1%
b0000100 '
b0000100 (
#71000000
#80000000
0!
0%
#90000000
1!
b0001000 #
1%
b0001000 '
b0001000 (
#91000000
#100000000
0!
0%
#110000000
1!
b0010000 #
1%
b0010000 '
b0010000 (
#111000000
#120000000
0!
0%
#130000000
1!
b0100000 #
1%
b0100000 '
b0100000 (
#131000000
#140000000
0!
0%
#150000000
1!
b1000000 #
1%
b1000000 '
b1000000 (
#151000000
#160000000
0!
0%
#170000000
1!
b0000001 #
1%
b0000001 '
b0000001 (
#171000000
#180000000
0!
0%
#190000000
1!
b0000010 #
1%
b0000010 '
b0000010 (
#200000000
0!
0%
#210000000
1!
b0000100 #
1%
b0000100 '
b0000100 (
#211000000
1"
b0000001 #
1&
b0000001 '
b0000001 (
#220000000
0!
0%
#230000000
1!
1%
#231000000
0"
0&
#240000000
0!
0%
#250000000
1!
b0000010 #
1%
b0000010 '
b0000010 (
#251000000
1$
