src/framebuffer_decoder/framebuffer_decoder.vhd
library ieee;
use ieee.std_logic_1164.all;
use ieee.numeric_std.all;

entity framebuffer_decoder is
    port (
        clk       : in  std_logic;                    -- System clock
        rst       : in  std_logic;                    -- Global reset
        load_fb   : in  std_logic;                    -- Write enable / latch signal
        data_in   : in  std_logic_vector(3 downto 0); -- 4-bit data input
        fb_out    : out std_logic_vector(3 downto 0); -- Latched 4-bit pixel state
        ansi_char : out std_logic_vector(7 downto 0)  -- 8-bit ASCII character encoding
    );
end entity framebuffer_decoder;

architecture behavioral of framebuffer_decoder is
    signal fb_reg : std_logic_vector(3 downto 0) := (others => '0');
begin

    -- Synchronous Latch Process
    process(clk, rst)
    begin
        if rst = '1' then
            fb_reg <= (others => '0');
        elsif rising_edge(clk) then
            if load_fb = '1' then
                fb_reg <= data_in;
            end if;
        end if;
    end process;

    fb_out <= fb_reg;

    -- Monochrome Display Decoder (4-bit intensity / symbol mapping to ASCII)
    process(fb_reg)
    begin
        case fb_reg is
            when "0000" => ansi_char <= x"20"; -- ' ' (Space / Off)
            when "0001" => ansi_char <= x"2E"; -- '.'
            when "0010" => ansi_char <= x"3A"; -- ':'
            when "0011" => ansi_char <= x"2D"; -- '-'
            when "0100" => ansi_char <= x"3D"; -- '='
            when "0101" => ansi_char <= x"2B"; -- '+'
            when "0110" => ansi_char <= x"2A"; -- '*'
            when "0111" => ansi_char <= x"23"; -- '#'
            when "1000" => ansi_char <= x"25"; -- '%'
            when "1001" => ansi_char <= x"40"; -- '@' (Bright)
            when "1010" => ansi_char <= x"30"; -- '0'
            when "1011" => ansi_char <= x"31"; -- '1'
            when "1100" => ansi_char <= x"32"; -- '2'
            when "1101" => ansi_char <= x"33"; -- '3'
            when "1110" => ansi_char <= x"34"; -- '4'
            when "1111" => ansi_char <= x"57"; -- 'W' (Full intensity)
            when others => ansi_char <= x"20";
        end case;
    end process;

end architecture behavioral;

tb/unit/framebuffer_decoder/tb_framebuffer_decoder.vhd
library ieee;
use ieee.std_logic_1164.all;

entity tb_framebuffer_decoder is
end entity tb_framebuffer_decoder;

architecture sim of tb_framebuffer_decoder is

    constant CLK_PERIOD : time := 20 ns;

    signal clk       : std_logic := '0';
    signal rst       : std_logic := '0';
    signal load_fb   : std_logic := '0';
    signal data_in   : std_logic_vector(3 downto 0) := (others => '0');
    
    signal fb_out    : std_logic_vector(3 downto 0);
    signal ansi_char : std_logic_vector(7 downto 0);

    signal sim_end   : boolean := false;

begin

    -- Instantiate Unit Under Test
    uut: entity work.framebuffer_decoder
        port map (
            clk       => clk,
            rst       => rst,
            load_fb   => load_fb,
            data_in   => data_in,
            fb_out    => fb_out,
            ansi_char => ansi_char
        );

    -- Clock Generation
    clk_gen: process
    begin
        while not sim_end loop
            clk <= '0';
            wait for CLK_PERIOD / 2;
            clk <= '1';
            wait for CLK_PERIOD / 2;
        end loop;
        wait;
    end process;

    -- Stimulus Process
    stim_proc: process
    begin
        report "--- Starting Framebuffer Decoder Unit Test ---";

        -- Test Case 1: Global Reset
        rst <= '1';
        wait for 40 ns;
        assert fb_out = "0000" and ansi_char = x"20"
            report "FAIL: Framebuffer failed to initialize to '0000' (space)" severity failure;
        
        rst <= '0';
        wait for 20 ns;
        report "SUCCESS: Reset initialized framebuffer properly.";

        -- Test Case 2: Load '0001' (Pixel level 1 -> '.')
        report "--- Case 2: Loading '0001' ---";
        wait until falling_edge(clk);
        data_in <= "0001";
        load_fb <= '1';

        wait until rising_edge(clk);
        wait for 1 ns;
        assert fb_out = "0001" and ansi_char = x"2E"
            report "FAIL: Framebuffer did not output '.' (0x2E) for 0001" severity failure;
        report "SUCCESS: Framebuffer loaded '0001' -> ASCII '.'";

        -- Test Case 3: Hold Value when load_fb = '0'
        report "--- Case 3: Verify Hold State ---";
        load_fb <= '0';
        data_in <= "1001"; -- Input changes, register should hold "0001"
        wait until rising_edge(clk);
        wait for 1 ns;
        assert fb_out = "0001"
            report "FAIL: Framebuffer updated value without load_fb signal" severity failure;

        -- Test Case 4: Load '1001' (Pixel level 9 -> '@')
        report "--- Case 4: Loading '1001' ---";
        wait until falling_edge(clk);
        data_in <= "1001";
        load_fb <= '1';

        wait until rising_edge(clk);
        wait for 1 ns;
        assert fb_out = "1001" and ansi_char = x"40"
            report "FAIL: Framebuffer did not output '@' (0x40) for 1001" severity failure;
        report "SUCCESS: Framebuffer loaded '1001' -> ASCII '@'";

        load_fb <= '0';
        wait for 20 ns;

        sim_end <= true;
        report "=== FRAMEBUFFER DECODER TEST PASSED ===";
        wait;
    end process;

end architecture sim;

wave/unit/framebuffer_decoder/waveform.vcd
$date
  Sat Sep 19 19:21:11 2026
$end
$version
  GHDL v0
$end
$timescale
  1 fs
$end
$scope module standard $end
$upscope $end
$scope module textio $end
$upscope $end
$scope module std_logic_1164 $end
$upscope $end
$scope module numeric_std $end
$upscope $end
$scope module tb_framebuffer_decoder $end
$var reg 1 ! clk $end
$var reg 1 " rst $end
$var reg 1 # load_fb $end
$var reg 4 $ data_in[3:0] $end
$var reg 4 % fb_out[3:0] $end
$var reg 8 & ansi_char[7:0] $end
$var reg 1 ' sim_end $end
$scope module uut $end
$var reg 1 ( clk $end
$var reg 1 ) rst $end
$var reg 1 * load_fb $end
$var reg 4 + data_in[3:0] $end
$var reg 4 , fb_out[3:0] $end
$var reg 8 - ansi_char[7:0] $end
$var reg 4 . fb_reg[3:0] $end
$upscope $end
$upscope $end
$enddefinitions $end
#0
0!
1"
0#
b0000 $
b0000 %
b00100000 &
0'
0(
1)
0*
b0000 +
b0000 ,
b00100000 -
b0000 .
#10000000
1!
1(
#20000000
0!
0(
#30000000
1!
1(
#40000000
0!
0"
0(
0)
#50000000
1!
1(
#60000000
0!
1#
b0001 $
0(
1*
b0001 +
#70000000
1!
b0001 %
b00101110 &
1(
b0001 ,
b00101110 -
b0001 .
#71000000
0#
b1001 $
0*
b1001 +
#80000000
0!
0(
#90000000
1!
1(
#91000000
#100000000
0!
1#
0(
1*
#110000000
1!
b1001 %
b01000000 &
1(
b1001 ,
b01000000 -
b1001 .
#111000000
0#
0*
#120000000
0!
0(
#130000000
1!
1(
#131000000
1'
