src/clock/clock.vhd
library ieee;
use ieee.std_logic_1164.all;

entity clock is
    port (
        clk_in  : in  std_logic;  -- Primary oscillator input
        rst     : in  std_logic;  -- Global reset (active high)
        hlt     : in  std_logic;  -- Halt signal from opcode decoder
        clk_out : out std_logic   -- Gated system clock output
    );
end entity clock;

architecture behavioral of clock is
    signal halted : std_logic := '0';
begin

    process(clk_in, rst)
    begin
        if rst = '1' then
            halted <= '0';
        elsif rising_edge(clk_in) then
            if hlt = '1' then
                halted <= '1';
            end if;
        end if;
    end process;

    -- Gate the output clock: stopped when halted or reset
    clk_out <= clk_in and (not halted) and (not rst);

end architecture behavioral;

tb/unit/clock/tb_clock.vhd
library ieee;
use ieee.std_logic_1164.all;

entity tb_clock is
end entity tb_clock;

architecture sim of tb_clock is

    constant CLK_PERIOD : time := 20 ns;
    
    signal clk_in  : std_logic := '0';
    signal rst     : std_logic := '0';
    signal hlt     : std_logic := '0';
    signal clk_out : std_logic;
    
    signal sim_end : boolean := false;

begin

    -- Instantiate Unit Under Test (UUT)
    uut: entity work.clock
        port map (
            clk_in  => clk_in,
            rst     => rst,
            hlt     => hlt,
            clk_out => clk_out
        );

    -- Master Clock Oscillator Process
    clk_gen: process
    begin
        while not sim_end loop
            clk_in <= '0';
            wait for CLK_PERIOD / 2;
            clk_in <= '1';
            wait for CLK_PERIOD / 2;
        end loop;
        wait;
    end process;

    -- Test Stimulus Process
    stim_proc: process
    begin
        report "--- Starting Clock Unit Test ---";
        
        -- Test Case 1: Initial Reset
        rst <= '1';
        wait for 40 ns;
        assert clk_out = '0' 
            report "FAIL: clk_out should be suppressed during reset" severity failure;
        
        -- Release Reset -> Clock should start toggling
        rst <= '0';
        wait for 100 ns;
        assert clk_out'event or clk_out = clk_in 
            report "FAIL: clk_out should toggle after reset release" severity failure;
        
        -- Test Case 2: Trigger Halt
        report "--- Triggering Halt Signal ---";
        wait until falling_edge(clk_in);
        hlt <= '1';
        wait for 40 ns;
        hlt <= '0';
        
        -- Verify output clock freezes
        wait for 60 ns;
        assert clk_out = '0' 
            report "FAIL: clk_out did not freeze after HLT signal assertion" severity failure;
        report "SUCCESS: Clock halted as expected.";

        -- Test Case 3: Re-reset System
        report "--- Resetting Halted System ---";
        rst <= '1';
        wait for 40 ns;
        rst <= '0';
        wait for 60 ns;
        
        assert clk_out'event or clk_out = clk_in 
            report "FAIL: clk_out did not resume after reset" severity failure;
        report "SUCCESS: Clock resumed after reset.";

        sim_end <= true;
        report "=== CLOCK MODULE TEST PASSED ===";
        wait;
    end process;

end architecture sim;

wave/unit/clock/waveform.vcd
$date
  Sat Sep 19 15:32:01 2026
$end
$version
  GHDL v0
$end
$timescale
  1 fs
$end
$scope module standard $end
$upscope $end
$scope module textio $end
$upscope $end
$scope module std_logic_1164 $end
$upscope $end
$scope module tb_clock $end
$var reg 1 ! clk_in $end
$var reg 1 " rst $end
$var reg 1 # hlt $end
$var reg 1 $ clk_out $end
$var reg 1 % sim_end $end
$scope module uut $end
$var reg 1 & clk_in $end
$var reg 1 ' rst $end
$var reg 1 ( hlt $end
$var reg 1 ) clk_out $end
$var reg 1 * halted $end
$upscope $end
$upscope $end
$enddefinitions $end
#0
0!
1"
0#
0$
0%
0&
1'
0(
0)
0*
#10000000
1!
1&
#20000000
0!
0&
#30000000
1!
1&
#40000000
0!
0"
0&
0'
#50000000
1!
1$
1&
1)
#60000000
0!
0$
0&
0)
#70000000
1!
1$
1&
1)
#80000000
0!
0$
0&
0)
#90000000
1!
1$
1&
1)
#100000000
0!
0$
0&
0)
#110000000
1!
1$
1&
1)
#120000000
0!
0$
0&
0)
#130000000
1!
1$
1&
1)
#140000000
0!
1#
0$
0&
1(
0)
#150000000
1!
0$
1&
0)
1*
#160000000
0!
0&
#170000000
1!
1&
#180000000
0!
0#
0&
0(
#190000000
1!
1&
#200000000
0!
0&
#210000000
1!
1&
#220000000
0!
0&
#230000000
1!
1&
#240000000
0!
1"
0&
1'
0*
#250000000
1!
1&
#260000000
0!
0&
#270000000
1!
1&
#280000000
0!
0"
0&
0'
#290000000
1!
1$
1&
1)
#300000000
0!
0$
0&
0)
#310000000
1!
1$
1&
1)
#320000000
0!
0$
0&
0)
#330000000
1!
1$
1&
1)
#340000000
0!
0$
1%
0&
0)
