src/a_register/a_register.vhd
library ieee;
use ieee.std_logic_1164.all;

entity a_register is
    port (
        clk      : in    std_logic;                    -- System clock
        rst      : in    std_logic;                    -- Global reset (active high)
        load_a   : in    std_logic;                    -- Load enable from control matrix
        en_a_bus : in    std_logic;                    -- Bus driver enable (tri-state)
        data_bus : inout std_logic_vector(3 downto 0); -- Shared 4-bit Data Bus
        a_out    : out   std_logic_vector(3 downto 0)  -- Dedicated 4-bit output to ALU
    );
end entity a_register;

architecture behavioral of a_register is
    signal reg_val : std_logic_vector(3 downto 0) := (others => '0');
begin

    process(clk, rst)
    begin
        if rst = '1' then
            reg_val <= (others => '0');
        elsif rising_edge(clk) then
            if load_a = '1' then
                reg_val <= data_bus;
            end if;
        end if;
    end process;

    -- Tri-state output to Data Bus
    data_bus <= reg_val when en_a_bus = '1' else (others => 'Z');

    -- Continuous output to ALU
    a_out <= reg_val;

end architecture behavioral;

tb/unit/a_register/tb_a_register.vhd
library ieee;
use ieee.std_logic_1164.all;

entity tb_a_register is
end entity tb_a_register;

architecture sim of tb_a_register is

    constant CLK_PERIOD : time := 20 ns;

    signal clk      : std_logic := '0';
    signal rst      : std_logic := '0';
    signal load_a   : std_logic := '0';
    signal en_a_bus : std_logic := '0';
    
    signal data_bus : std_logic_vector(3 downto 0) := (others => 'Z');
    signal a_out    : std_logic_vector(3 downto 0);
    
    -- Testbench bus driver signal
    signal tb_drive_bus : std_logic_vector(3 downto 0) := (others => 'Z');
    signal sim_end      : boolean := false;

begin

    -- Tri-state driving of shared data bus from testbench
    data_bus <= tb_drive_bus;

    -- Instantiate UUT
    uut: entity work.a_register
        port map (
            clk      => clk,
            rst      => rst,
            load_a   => load_a,
            en_a_bus => en_a_bus,
            data_bus => data_bus,
            a_out    => a_out
        );

    -- Clock Process
    clk_gen: process
    begin
        while not sim_end loop
            clk <= '0';
            wait for CLK_PERIOD / 2;
            clk <= '1';
            wait for CLK_PERIOD / 2;
        end loop;
        wait;
    end process;

    -- Stimulus Process
    stim_proc: process
    begin
        report "--- Starting Register A Unit Test ---";

        -- Reset check
        rst <= '1';
        wait for 40 ns;
        assert a_out = "0000" report "FAIL: Register A reset failed" severity failure;
        rst <= '0';
        wait for 20 ns;

        -- Test Case 1: Load "1010" from Data Bus
        report "--- Case 1: Loading 1010 into Register A ---";
        wait until falling_edge(clk);
        tb_drive_bus <= "1010";
        load_a       <= '1';
        
        wait until rising_edge(clk);
        wait for 1 ns;
        assert a_out = "1010" report "FAIL: Register A did not store 1010" severity failure;
        report "SUCCESS: Register A loaded 1010 to ALU output port.";

        -- Test Case 2: Hold value when load_a = '0'
        report "--- Case 2: Holding stored value ---";
        load_a       <= '0';
        tb_drive_bus <= "1111"; -- Bus changes, register should hold "1010"
        wait until rising_edge(clk);
        wait for 1 ns;
        assert a_out = "1010" report "FAIL: Register A changed without load signal!" severity failure;

        -- Test Case 3: Drive Data Bus Output (Tri-State)
        report "--- Case 3: Bus Driver Enable (en_a_bus) ---";
        tb_drive_bus <= (others => 'Z'); -- Release testbench bus drive
        wait for 10 ns;
        assert data_bus = "ZZZZ" report "FAIL: Bus should be high-Z when disabled" severity failure;

        en_a_bus <= '1';
        wait for 10 ns;
        assert data_bus = "1010" report "FAIL: Register A failed to drive 1010 onto Data Bus" severity failure;
        report "SUCCESS: Register A drove 1010 onto Data Bus.";

        en_a_bus <= '0';
        wait for 10 ns;
        assert data_bus = "ZZZZ" report "FAIL: Bus did not return to high-Z" severity failure;

        sim_end <= true;
        report "=== REGISTER A TEST PASSED ===";
        wait;
    end process;

end architecture sim;

wave/unit/a-register/waveform.vcd
$date
  Sat Sep 19 15:54:14 2026
$end
$version
  GHDL v0
$end
$timescale
  1 fs
$end
$scope module standard $end
$upscope $end
$scope module textio $end
$upscope $end
$scope module std_logic_1164 $end
$upscope $end
$scope module tb_a_register $end
$var reg 1 ! clk $end
$var reg 1 " rst $end
$var reg 1 # load_a $end
$var reg 1 $ en_a_bus $end
$var reg 4 % data_bus[3:0] $end
$var reg 4 & a_out[3:0] $end
$var reg 4 ' tb_drive_bus[3:0] $end
$var reg 1 ( sim_end $end
$scope module uut $end
$var reg 1 ) clk $end
$var reg 1 * rst $end
$var reg 1 + load_a $end
$var reg 1 , en_a_bus $end
$var reg 4 - data_bus[3:0] $end
$var reg 4 . a_out[3:0] $end
$var reg 4 / reg_val[3:0] $end
$upscope $end
$upscope $end
$enddefinitions $end
#0
0!
1"
0#
0$
bZZZZ %
b0000 &
bZZZZ '
0(
0)
1*
0+
0,
bZZZZ -
b0000 .
b0000 /
#10000000
1!
1)
#20000000
0!
0)
#30000000
1!
1)
#40000000
0!
0"
0)
0*
#50000000
1!
1)
#60000000
0!
1#
b1010 %
b1010 '
0)
1+
b1010 -
#70000000
1!
b1010 &
1)
b1010 .
b1010 /
#71000000
0#
b1111 %
b1111 '
0+
b1111 -
#80000000
0!
0)
#90000000
1!
1)
#91000000
bZZZZ %
bZZZZ '
bZZZZ -
#100000000
0!
0)
#101000000
1$
b1010 %
1,
b1010 -
#110000000
1!
1)
#111000000
0$
bZZZZ %
0,
bZZZZ -
#120000000
0!
0)
#121000000
1(
