src/opcode_decoder/opcode_decoder.vhd
library ieee;
use ieee.std_logic_1164.all;

entity opcode_decoder is
    port (
        clk         : in  std_logic;                     -- System clock
        rst         : in  std_logic;                     -- Global reset
        data_bus    : in  std_logic_vector(3 downto 0);  -- Shared 4-bit Data Bus
        t_in        : in  std_logic_vector(6 downto 0);  -- 7-bit T-state vector from Ring Counter
        
        -- Control Signal Outputs
        inc_pc      : out std_logic;                     -- Increment Program Counter
        en_mem_bus  : out std_logic;                     -- Enable Memory output to Data Bus
        load_a      : out std_logic;                     -- Load Register A
        en_a_bus    : out std_logic;                     -- Enable Register A output to Data Bus
        load_b      : out std_logic;                     -- Load Register B
        en_sub      : out std_logic;                     -- ALU Subtract control
        en_alu_bus  : out std_logic;                     -- Enable ALU output to Data Bus
        step_lfsr   : out std_logic;                     -- Trigger LFSR state update
        en_lfsr_bus : out std_logic;                     -- Enable LFSR output to Data Bus
        hlt         : out std_logic;                     -- System Halt signal
        op_out      : out std_logic_vector(3 downto 0)   -- Latched opcode output
    );
end entity opcode_decoder;

architecture behavioral of opcode_decoder is
    signal ir_reg : std_logic_vector(3 downto 0) := (others => '0');
begin

    -- Instruction Register Latch Process (Latches on T1 timing state)
    process(clk, rst)
    begin
        if rst = '1' then
            ir_reg <= "0000";
        elsif rising_edge(clk) then
            if t_in(0) = '1' then -- T1 state: Latch instruction from memory bus
                ir_reg <= data_bus;
            end if;
        end if;
    end process;

    op_out <= ir_reg;

    -- Combinational Control Matrix Decoder
    process(ir_reg, t_in)
    begin
        -- Default control signal states (Inactive)
        inc_pc      <= '0';
        en_mem_bus  <= '0';
        load_a      <= '0';
        en_a_bus    <= '0';
        load_b      <= '0';
        en_sub      <= '0';
        en_alu_bus  <= '0';
        step_lfsr   <= '0';
        en_lfsr_bus <= '0';
        hlt         <= '0';

        -- Common Fetch Micro-operations:
        -- T1: Memory drives Data Bus (Opcode latch handled in process above)
        if t_in(0) = '1' then
            en_mem_bus <= '1';
        -- T2: Increment PC to point to next instruction / operand
        elsif t_in(1) = '1' then
            inc_pc <= '1';
        
        -- Instruction Execution Micro-operations (T3 - T7)
        else
            case ir_reg is
                when "0001" => -- LDA: Load Memory to Register A
                    if t_in(2) = '1' then -- T3
                        en_mem_bus <= '1';
                        load_a     <= '1';
                    end if;

                when "0010" => -- ADD: Reg A = Reg A + Reg B
                    if t_in(2) = '1' then -- T3
                        en_alu_bus <= '1';
                        en_sub     <= '0';
                        load_a     <= '1';
                    end if;

                when "0011" => -- SUB: Reg A = Reg A - Reg B
                    if t_in(2) = '1' then -- T3
                        en_alu_bus <= '1';
                        en_sub     <= '1';
                        load_a     <= '1';
                    end if;

                when "0100" => -- LDB: Load Memory to Register B
                    if t_in(2) = '1' then -- T3
                        en_mem_bus <= '1';
                        load_b     <= '1';
                    end if;

                when "0101" => -- RND: Step LFSR and store in Reg A
                    if t_in(2) = '1' then -- T3: Step LFSR logic
                        step_lfsr <= '1';
                    elsif t_in(3) = '1' then -- T4: Put LFSR result into Reg A
                        en_lfsr_bus <= '1';
                        load_a      <= '1';
                    end if;

                when "1111" => -- HLT: Assert System Halt
                    if t_in(2) = '1' then -- T3
                        hlt <= '1';
                    end if;

                when others =>
                    null; -- NOP or unmapped opcodes
            end case;
        end if;
    end process;

end architecture behavioral;

tb/unit/opcode_decoder/tb_opcode_decoder.vhd
library ieee;
use ieee.std_logic_1164.all;

entity tb_opcode_decoder is
end entity tb_opcode_decoder;

architecture sim of tb_opcode_decoder is

    constant CLK_PERIOD : time := 20 ns;

    signal clk         : std_logic := '0';
    signal rst         : std_logic := '0';
    signal data_bus    : std_logic_vector(3 downto 0) := (others => '0');
    signal t_in        : std_logic_vector(6 downto 0) := "0000001"; -- Start at T1

    -- Control Signals
    signal inc_pc      : std_logic;
    signal en_mem_bus  : std_logic;
    signal load_a      : std_logic;
    signal en_a_bus    : std_logic;
    signal load_b      : std_logic;
    signal en_sub      : std_logic;
    signal en_alu_bus  : std_logic;
    signal step_lfsr   : std_logic;
    signal en_lfsr_bus : std_logic;
    signal hlt         : std_logic;
    signal op_out      : std_logic_vector(3 downto 0);

    signal sim_end     : boolean := false;

begin

    uut: entity work.opcode_decoder
        port map (
            clk         => clk,
            rst         => rst,
            data_bus    => data_bus,
            t_in        => t_in,
            inc_pc      => inc_pc,
            en_mem_bus  => en_mem_bus,
            load_a      => load_a,
            en_a_bus    => en_a_bus,
            load_b      => load_b,
            en_sub      => en_sub,
            en_alu_bus  => en_alu_bus,
            step_lfsr   => step_lfsr,
            en_lfsr_bus => en_lfsr_bus,
            hlt         => hlt,
            op_out      => op_out
        );

    clk_gen: process
    begin
        while not sim_end loop
            clk <= '0';
            wait for CLK_PERIOD / 2;
            clk <= '1';
            wait for CLK_PERIOD / 2;
        end loop;
        wait;
    end process;

    stim_proc: process
    begin
        report "--- Starting Opcode Decoder Unit Test ---";

        -- Reset Check
        rst <= '1';
        wait for 40 ns;
        rst <= '0';
        wait for 20 ns;

        ------------------------------------------------------------------
        -- Test Case 1: Fetch Cycle & ADD Instruction Decode ("0010")
        ------------------------------------------------------------------
        report "--- Case 1: Fetch and Decode ADD Instruction ('0010') ---";
        data_bus <= "0010"; -- ADD opcode on bus
        t_in     <= "0000001"; -- T1
        wait for 5 ns;
        assert en_mem_bus = '1' report "FAIL: T1 should assert en_mem_bus" severity failure;

        wait until rising_edge(clk); -- Clock latches Opcode in T1
        wait for 1 ns;
        assert op_out = "0010" report "FAIL: Opcode 0010 not latched" severity failure;

        -- Move to T2
        t_in <= "0000010"; -- T2
        wait for 5 ns;
        assert inc_pc = '1' report "FAIL: T2 should assert inc_pc" severity failure;

        -- Move to T3 (Execution Phase of ADD)
        t_in <= "0000100"; -- T3
        wait for 5 ns;
        assert en_alu_bus = '1' and load_a = '1' and en_sub = '0'
            report "FAIL: ADD execution control signals incorrect" severity failure;
        report "SUCCESS: ADD instruction decoded properly.";

        ------------------------------------------------------------------
        -- Test Case 2: SUB Instruction Decode ("0011")
        ------------------------------------------------------------------
        report "--- Case 2: Decode SUB Instruction ('0011') ---";
        data_bus <= "0011";
        t_in     <= "0000001"; -- T1
        wait until rising_edge(clk);
        
        t_in <= "0000100"; -- Jump to T3
        wait for 5 ns;
        assert en_alu_bus = '1' and load_a = '1' and en_sub = '1'
            report "FAIL: SUB execution control signals incorrect" severity failure;
        report "SUCCESS: SUB instruction decoded properly.";

        ------------------------------------------------------------------
        -- Test Case 3: HLT Instruction Decode ("1111")
        ------------------------------------------------------------------
        report "--- Case 3: Decode HLT Instruction ('1111') ---";
        data_bus <= "1111";
        t_in     <= "0000001"; -- T1
        wait until rising_edge(clk);
        
        t_in <= "0000100"; -- T3
        wait for 5 ns;
        assert hlt = '1' report "FAIL: HLT signal not asserted" severity failure;
        report "SUCCESS: HLT instruction decoded properly.";

        sim_end <= true;
        report "=== OPCODE DECODER TEST PASSED ===";
        wait;
    end process;

end architecture sim;

wave/unit/opcode-decoder/waveform.vcd
$date
  Sat Sep 19 18:56:59 2026
$end
$version
  GHDL v0
$end
$timescale
  1 fs
$end
$scope module standard $end
$upscope $end
$scope module textio $end
$upscope $end
$scope module std_logic_1164 $end
$upscope $end
$scope module tb_opcode_decoder $end
$var reg 1 ! clk $end
$var reg 1 " rst $end
$var reg 4 # data_bus[3:0] $end
$var reg 7 $ t_in[6:0] $end
$var reg 1 % inc_pc $end
$var reg 1 & en_mem_bus $end
$var reg 1 ' load_a $end
$var reg 1 ( en_a_bus $end
$var reg 1 ) load_b $end
$var reg 1 * en_sub $end
$var reg 1 + en_alu_bus $end
$var reg 1 , step_lfsr $end
$var reg 1 - en_lfsr_bus $end
$var reg 1 . hlt $end
$var reg 4 / op_out[3:0] $end
$var reg 1 0 sim_end $end
$scope module uut $end
$var reg 1 1 clk $end
$var reg 1 2 rst $end
$var reg 4 3 data_bus[3:0] $end
$var reg 7 4 t_in[6:0] $end
$var reg 1 5 inc_pc $end
$var reg 1 6 en_mem_bus $end
$var reg 1 7 load_a $end
$var reg 1 8 en_a_bus $end
$var reg 1 9 load_b $end
$var reg 1 : en_sub $end
$var reg 1 ; en_alu_bus $end
$var reg 1 < step_lfsr $end
$var reg 1 = en_lfsr_bus $end
$var reg 1 > hlt $end
$var reg 4 ? op_out[3:0] $end
$var reg 4 @ ir_reg[3:0] $end
$upscope $end
$upscope $end
$enddefinitions $end
#0
0!
1"
b0000 #
b0000001 $
0%
1&
0'
0(
0)
0*
0+
0,
0-
0.
b0000 /
00
01
12
b0000 3
b0000001 4
05
16
07
08
09
0:
0;
0<
0=
0>
b0000 ?
b0000 @
#10000000
1!
11
#20000000
0!
01
#30000000
1!
11
#40000000
0!
0"
01
02
#50000000
1!
11
#60000000
0!
b0010 #
01
b0010 3
#65000000
#70000000
1!
b0010 /
11
16
b0010 ?
b0010 @
#71000000
b0000010 $
1%
0&
b0000010 4
15
06
#76000000
b0000100 $
0%
1'
1+
b0000100 4
05
17
1;
#80000000
0!
01
#81000000
b0011 #
b0000001 $
1&
0'
0+
b0011 3
b0000001 4
16
07
0;
#90000000
1!
b0000100 $
0&
1'
1*
1+
b0011 /
11
b0000100 4
06
17
1:
1;
b0011 ?
b0011 @
#95000000
b1111 #
b0000001 $
1&
0'
0*
0+
b1111 3
b0000001 4
16
07
0:
0;
#100000000
0!
01
#110000000
1!
b0000100 $
0&
1.
b1111 /
11
b0000100 4
06
1>
b1111 ?
b1111 @
#115000000
10
