src/memory/memory.vhd
library ieee;
use ieee.std_logic_1164.all;
use ieee.numeric_std.all;

entity memory is
    port (
        clk        : in    std_logic;                    -- System clock
        rst        : in    std_logic;                    -- Global reset (loads initial program/data)
        addr       : in    std_logic_vector(3 downto 0); -- 4-bit memory address input (0 to 15)
        write_en   : in    std_logic;                    -- Memory write enable
        en_mem_bus : in    std_logic;                    -- Output enable to Data Bus (tri-state)
        data_bus   : inout std_logic_vector(3 downto 0); -- Shared 4-bit Data Bus
        mem_out    : out   std_logic_vector(3 downto 0)  -- Direct read port output
    );
end entity memory;

architecture behavioral of memory is

    -- 16-word x 4-bit memory array type (covering full 4-bit address space)
    type ram_type is array (0 to 15) of std_logic_vector(3 downto 0);

    -- Default preloaded program / test pattern (Addresses 0 to 9 map to GSN477 Bytes 1-10)
    constant INIT_RAM : ram_type := (
        0 => "0001", -- Address 0 (Byte 1)
        1 => "0010", -- Address 1 (Byte 2)
        2 => "0100", -- Address 2 (Byte 3)
        3 => "1000", -- Address 3 (Byte 4)
        4 => "0011", -- Address 4 (Byte 5)
        5 => "0110", -- Address 5 (Byte 6)
        6 => "1100", -- Address 6 (Byte 7)
        7 => "1001", -- Address 7 (Byte 8)
        8 => "1111", -- Address 8 (Byte 9)
        9 => "0101", -- Address 9 (Byte 10)
        others => "0000"
    );

    signal ram : ram_type := INIT_RAM;
    signal current_data : std_logic_vector(3 downto 0);

begin

    -- Synchronous Write & Reset Process
    process(clk, rst)
        variable idx : integer range 0 to 15;
    begin
        if rst = '1' then
            ram <= INIT_RAM;
        elsif rising_edge(clk) then
            idx := to_integer(unsigned(addr));
            if write_en = '1' then
                ram(idx) <= data_bus;
            end if;
        end if;
    end process;

    -- Asynchronous Read Output
    current_data <= ram(to_integer(unsigned(addr)));
    mem_out      <= current_data;

    -- Tri-State Driver to Data Bus
    data_bus <= current_data when en_mem_bus = '1' else (others => 'Z');

end architecture behavioral;

tb/unit/memory/tb_memory.vhd
library ieee;
use ieee.std_logic_1164.all;
use ieee.numeric_std.all;

entity tb_memory is
end entity tb_memory;

architecture sim of tb_memory is

    constant CLK_PERIOD : time := 20 ns;

    signal clk        : std_logic := '0';
    signal rst        : std_logic := '0';
    signal addr       : std_logic_vector(3 downto 0) := (others => '0');
    signal write_en   : std_logic := '0';
    signal en_mem_bus : std_logic := '0';

    signal data_bus   : std_logic_vector(3 downto 0) := (others => 'Z');
    signal mem_out    : std_logic_vector(3 downto 0);

    signal tb_drive_bus : std_logic_vector(3 downto 0) := (others => 'Z');
    signal sim_end      : boolean := false;

begin

    -- Driver connection for writing to memory from testbench
    data_bus <= tb_drive_bus;

    -- Instantiate Unit Under Test
    uut: entity work.memory
        port map (
            clk        => clk,
            rst        => rst,
            addr       => addr,
            write_en   => write_en,
            en_mem_bus => en_mem_bus,
            data_bus   => data_bus,
            mem_out    => mem_out
        );

    -- Clock Generation
    clk_gen: process
    begin
        while not sim_end loop
            clk <= '0';
            wait for CLK_PERIOD / 2;
            clk <= '1';
            wait for CLK_PERIOD / 2;
        end loop;
        wait;
    end process;

    -- Stimulus Process
    stim_proc: process
    begin
        report "--- Starting Memory Unit Test ---";

        -- Test Case 1: Initial Reset and Default Contents Check
        rst <= '1';
        wait for 40 ns;
        rst <= '0';
        wait for 20 ns;

        report "--- Case 1: Checking Preloaded RAM Values ---";
        addr <= "0000"; -- Address 0
        wait for 5 ns;
        assert mem_out = "0001" 
            report "FAIL: Addr 0 expected 0001, got " & to_string(mem_out) severity failure;

        addr <= "0001"; -- Address 1
        wait for 5 ns;
        assert mem_out = "0010" 
            report "FAIL: Addr 1 expected 0010, got " & to_string(mem_out) severity failure;

        addr <= "1001"; -- Address 9 (Byte 10)
        wait for 5 ns;
        assert mem_out = "0101" 
            report "FAIL: Addr 9 expected 0101, got " & to_string(mem_out) severity failure;
        report "SUCCESS: Memory preloaded default contents verified.";

        -- Test Case 2: Bus Driving (en_mem_bus)
        report "--- Case 2: Bus Driving Enable ---";
        addr       <= "0010"; -- Address 2 (contains "0100")
        en_mem_bus <= '0';
        wait for 10 ns;
        assert data_bus = "ZZZZ" report "FAIL: Bus should be high-Z when en_mem_bus=0" severity failure;

        en_mem_bus <= '1';
        wait for 10 ns;
        assert data_bus = "0100" report "FAIL: Bus expected 0100 from Addr 2" severity failure;
        report "SUCCESS: Tri-state bus driver functional.";

        en_mem_bus <= '0';
        wait for 10 ns;

        -- Test Case 3: Synchronous Write Operation
        report "--- Case 3: Writing '1011' to Address 3 ---";
        wait until falling_edge(clk);
        addr         <= "0011";   -- Target Address 3
        tb_drive_bus <= "1011";   -- Data to write
        write_en     <= '1';

        wait until rising_edge(clk); -- Clock edge writes data
        wait for 1 ns;
        
        write_en     <= '0';
        tb_drive_bus <= (others => 'Z'); -- Release bus driver
        wait for 5 ns;

        assert mem_out = "1011" 
            report "FAIL: Addr 3 expected written value 1011, got " & to_string(mem_out) severity failure;
        report "SUCCESS: Synchronous memory write completed.";

        sim_end <= true;
        report "=== MEMORY MODULE TEST PASSED ===";
        wait;
    end process;

end architecture sim;

wave/unit/memory/waveform.vcd
$date
  Sat Sep 19 16:11:11 2026
$end
$version
  GHDL v0
$end
$timescale
  1 fs
$end
$scope module standard $end
$upscope $end
$scope module textio $end
$upscope $end
$scope module std_logic_1164 $end
$upscope $end
$scope module numeric_std $end
$upscope $end
$scope module tb_memory $end
$var reg 1 ! clk $end
$var reg 1 " rst $end
$var reg 4 # addr[3:0] $end
$var reg 1 $ write_en $end
$var reg 1 % en_mem_bus $end
$var reg 4 & data_bus[3:0] $end
$var reg 4 ' mem_out[3:0] $end
$var reg 4 ( tb_drive_bus[3:0] $end
$var reg 1 ) sim_end $end
$scope module uut $end
$var reg 1 * clk $end
$var reg 1 + rst $end
$var reg 4 , addr[3:0] $end
$var reg 1 - write_en $end
$var reg 1 . en_mem_bus $end
$var reg 4 / data_bus[3:0] $end
$var reg 4 0 mem_out[3:0] $end
$comment ram is not handled $end
$var reg 4 1 current_data[3:0] $end
$upscope $end
$upscope $end
$enddefinitions $end
#0
0!
1"
b0000 #
0$
0%
bZZZZ &
b0001 '
bZZZZ (
0)
0*
1+
b0000 ,
0-
0.
bZZZZ /
b0001 0
b0001 1
#10000000
1!
1*
#20000000
0!
0*
#30000000
1!
1*
#40000000
0!
0"
0*
0+
#50000000
1!
1*
#60000000
0!
0*
#65000000
b0001 #
b0010 '
b0001 ,
b0010 0
b0010 1
#70000000
1!
b1001 #
b0101 '
1*
b1001 ,
b0101 0
b0101 1
#75000000
b0010 #
b0100 '
b0010 ,
b0100 0
b0100 1
#80000000
0!
0*
#85000000
1%
b0100 &
1.
b0100 /
#90000000
1!
1*
#95000000
0%
bZZZZ &
0.
bZZZZ /
#100000000
0!
0*
#105000000
#110000000
1!
1*
#120000000
0!
b0011 #
1$
b1011 &
b1000 '
b1011 (
0*
b0011 ,
1-
b1011 /
b1000 0
b1000 1
#130000000
1!
b1011 '
1*
b1011 0
b1011 1
#131000000
0$
bZZZZ &
bZZZZ (
0-
bZZZZ /
#136000000
1)
